tflowclient/__init__.py
tflowclient/cdp_flow.py
tflowclient/conf.py
tflowclient/demo_flow.py
tflowclient/flow.py
tflowclient/logs_gateway.py
tflowclient/observer.py
tflowclient/ui.py
tflowclient/entrypoints/__init__.py
tflowclient/entrypoints/cdp.py
tflowclient/entrypoints/demo.py
tflowclient/entrypoints/dumppalette.py
tflowclient-0.7.0.dist-info/LICENSE-fr.txt
tflowclient-0.7.0.dist-info/LICENSE.txt
tflowclient-0.7.0.dist-info/METADATA
tflowclient-0.7.0.dist-info/WHEEL
tflowclient-0.7.0.dist-info/entry_points.txt
tflowclient-0.7.0.dist-info/top_level.txt
tflowclient-0.7.0.dist-info/RECORD
